transformermpc/__init__.py
transformermpc/data/__init__.py
transformermpc/data/dataset.py
transformermpc/data/qp_generator.py
transformermpc/demo/__init__.py
transformermpc/demo/demo.py
transformermpc/models/__init__.py
transformermpc/models/constraint_predictor.py
transformermpc/models/warm_start_predictor.py
transformermpc/training/__init__.py
transformermpc/training/trainer.py
transformermpc/utils/__init__.py
transformermpc/utils/metrics.py
transformermpc/utils/osqp_wrapper.py
transformermpc/utils/visualization.py
transformermpc-0.1.7.dist-info/licenses/LICENSE
transformermpc-0.1.7.dist-info/METADATA
transformermpc-0.1.7.dist-info/WHEEL
transformermpc-0.1.7.dist-info/entry_points.txt
transformermpc-0.1.7.dist-info/top_level.txt
transformermpc-0.1.7.dist-info/RECORD
