Metadata-Version: 2.4
Name: transformermpc
Version: 0.1.7
Summary: Accelerating Model Predictive Control via Neural Networks
Home-page: https://github.com/Vrushabh27/transformermpc
Author: Ahmed Khalil, Efstathios Bakolas
Author-email: Vrushabh Zinage <vrushabh.zinage@e.com>
Maintainer-email: Vrushabh Zinage <vrushabh.zinage@e.com>
License-Expression: MIT
Project-URL: Homepage, https://github.com/vrushabh/transformermpc
Project-URL: Bug Tracker, https://github.com/vrushabh/transformermpc/issues
Keywords: machine learning,model predictive control,quadratic programming
Classifier: Programming Language :: Python :: 3
Classifier: Operating System :: OS Independent
Requires-Python: >=3.7
License-File: LICENSE
Requires-Dist: numpy>=1.20.0
Requires-Dist: scipy>=1.7.0
Requires-Dist: torch>=1.9.0
Requires-Dist: osqp>=0.6.2
Requires-Dist: matplotlib>=3.4.0
Requires-Dist: pandas>=1.3.0
Requires-Dist: tqdm>=4.62.0
Requires-Dist: scikit-learn>=0.24.0
Requires-Dist: tensorboard>=2.7.0
Requires-Dist: quadprog>=0.1.11
Dynamic: home-page
Dynamic: license-file
Dynamic: requires-python
